marchingcubes/__init__.py
marchingcubes/constants.py
marchingcubes/shape.py
MarchingCubes-1.2.0.dist-info/LICENSE
MarchingCubes-1.2.0.dist-info/METADATA
MarchingCubes-1.2.0.dist-info/WHEEL
MarchingCubes-1.2.0.dist-info/top_level.txt
MarchingCubes-1.2.0.dist-info/RECORD
