Metadata-Version: 2.1
Name: MarchingCubes
Version: 1.2.0
Summary: A Python package to create a shape based on opensimplex noise
Author: Weebywoo
Project-URL: Repository, https://github.com/weebywoo/marchingcubes
Project-URL: Documentation, https://marchingcubes.readthedocs.io/en/latest/
Classifier: Programming Language :: Python :: 3
Classifier: License :: OSI Approved :: GNU Affero General Public License v3
Requires-Python: >=3.10
License-File: LICENSE
